mython3/__init__.py
mython3/newbuiltins.py
mython3/web.py
mython3-0.0.1.6.dist-info/METADATA
mython3-0.0.1.6.dist-info/WHEEL
mython3-0.0.1.6.dist-info/top_level.txt
mython3-0.0.1.6.dist-info/RECORD
