Metadata-Version: 2.1
Name: mython3
Version: 0.0.1.6
Summary: LOTS OF NEW METHODS!!!
Home-page: UNKNOWN
Author: Will F
Author-email: forsbergw82@gmail.com
License: UNKNOWN
Platform: UNKNOWN
Classifier: Programming Language :: Python :: 3
